metatensor/operations/__init__.py
metatensor/operations/_abs.py
metatensor/operations/_add.py
metatensor/operations/_allclose.py
metatensor/operations/_backend.py
metatensor/operations/_block_from_array.py
metatensor/operations/_checks.py
metatensor/operations/_detach.py
metatensor/operations/_dispatch.py
metatensor/operations/_divide.py
metatensor/operations/_dot.py
metatensor/operations/_drop_blocks.py
metatensor/operations/_empty_like.py
metatensor/operations/_equal.py
metatensor/operations/_equal_metadata.py
metatensor/operations/_filter_blocks.py
metatensor/operations/_is_contiguous.py
metatensor/operations/_join.py
metatensor/operations/_lstsq.py
metatensor/operations/_make_contiguous.py
metatensor/operations/_manipulate_dimension.py
metatensor/operations/_multiply.py
metatensor/operations/_one_hot.py
metatensor/operations/_ones_like.py
metatensor/operations/_pow.py
metatensor/operations/_random_like.py
metatensor/operations/_reduce_over_samples.py
metatensor/operations/_remove_gradients.py
metatensor/operations/_requires_grad.py
metatensor/operations/_slice.py
metatensor/operations/_solve.py
metatensor/operations/_sort.py
metatensor/operations/_split.py
metatensor/operations/_subtract.py
metatensor/operations/_unique_metadata.py
metatensor/operations/_utils.py
metatensor/operations/_zeros_like.py
metatensor_operations-0.3.4.dist-info/licenses/AUTHORS
metatensor_operations-0.3.4.dist-info/licenses/LICENSE
metatensor_operations-0.3.4.dist-info/METADATA
metatensor_operations-0.3.4.dist-info/WHEEL
metatensor_operations-0.3.4.dist-info/top_level.txt
metatensor_operations-0.3.4.dist-info/zip-safe
metatensor_operations-0.3.4.dist-info/RECORD
